cxr_service_client/__init__.py
cxr_service_client-0.0.3.dist-info/METADATA
cxr_service_client-0.0.3.dist-info/WHEEL
cxr_service_client-0.0.3.dist-info/top_level.txt
cxr_service_client-0.0.3.dist-info/RECORD
