Metadata-Version: 2.1
Name: cxr-service-client
Version: 0.0.3
Summary: CX Runner Service Client
Home-page: https://github.com/CiscoAandI/cxr_service_client
Author: Ava Thorn
Author-email: avthorn@cisco.com
License: UNKNOWN
Project-URL: Bug Reports, https://github.com/CiscoAandI/cxr_service_client/issues
Project-URL: Source, https://github.com/CiscoAandI/cxr_service_client/
Keywords: cx,cx_runner,service,cisco
Platform: UNKNOWN
Classifier: Topic :: Software Development :: Build Tools
Requires-Python: >=3.10
Requires-Dist: requests (==2.26.0)
Requires-Dist: werkzeug (==2.0.2)
